README.rst
setup.py
genutils/__init__.py
genutils/strings.py
genutils/tbnumbers.py
genutils.egg-info/PKG-INFO
genutils.egg-info/SOURCES.txt
genutils.egg-info/dependency_links.txt
genutils.egg-info/not-zip-safe
genutils.egg-info/requires.txt
genutils.egg-info/top_level.txt